junitparser/__init__.py
junitparser/__main__.py
junitparser/cli.py
junitparser/junitparser.py
junitparser/py.typed
junitparser/xunit2.py
junitparser-4.0.1.dist-info/licenses/LICENSE
junitparser-4.0.1.dist-info/METADATA
junitparser-4.0.1.dist-info/WHEEL
junitparser-4.0.1.dist-info/entry_points.txt
junitparser-4.0.1.dist-info/top_level.txt
junitparser-4.0.1.dist-info/RECORD
