Metadata-Version: 2.4
Name: junitparser
Version: 4.0.1
Summary: Manipulates JUnit/xUnit Result XML files
Author-email: Weiwei Wang <gastlygem@gmail.com>
License: Apache-2.0
Project-URL: Homepage, https://github.com/weiwei/junitparser
Project-URL: Issues, https://github.com/weiwei/junitparser/issues
Project-URL: Documentation, https://junitparser.readthedocs.io/
Keywords: junit,xunit,xml,parser
Classifier: Development Status :: 5 - Production/Stable
Classifier: Intended Audience :: Developers
Classifier: License :: OSI Approved :: Apache Software License
Classifier: Topic :: Text Processing
Classifier: Programming Language :: Python :: 3
Requires-Python: >=3.6
License-File: LICENSE
Dynamic: license-file
